openbb_sec/__init__.py
openbb_sec/models/__init__.py
openbb_sec/models/cik_map.py
openbb_sec/models/company_filings.py
openbb_sec/models/compare_company_facts.py
openbb_sec/models/equity_ftd.py
openbb_sec/models/equity_search.py
openbb_sec/models/etf_holdings.py
openbb_sec/models/form_13FHR.py
openbb_sec/models/htm_file.py
openbb_sec/models/insider_trading.py
openbb_sec/models/institutions_search.py
openbb_sec/models/latest_financial_reports.py
openbb_sec/models/management_discussion_analysis.py
openbb_sec/models/py.typed
openbb_sec/models/rss_litigation.py
openbb_sec/models/schema_files.py
openbb_sec/models/sec_filing.py
openbb_sec/models/sic_search.py
openbb_sec/models/symbol_map.py
openbb_sec/py.typed
openbb_sec/utils/__init__.py
openbb_sec/utils/definitions.py
openbb_sec/utils/form4.py
openbb_sec/utils/frames.py
openbb_sec/utils/helpers.py
openbb_sec/utils/parse_13f.py
openbb_sec/utils/py.typed
openbb_sec-1.4.4.dist-info/METADATA
openbb_sec-1.4.4.dist-info/WHEEL
openbb_sec-1.4.4.dist-info/entry_points.txt
openbb_sec-1.4.4.dist-info/RECORD
