Metadata-Version: 2.3
Name: openbb-sec
Version: 1.4.4
Summary: SEC extension for OpenBB
License: AGPL-3.0-only
Author: OpenBB Team
Author-email: hello@openbb.co
Requires-Python: >=3.9.21,<3.13
Classifier: License :: OSI Approved :: GNU Affero General Public License v3
Classifier: Programming Language :: Python :: 3
Classifier: Programming Language :: Python :: 3.10
Classifier: Programming Language :: Python :: 3.11
Classifier: Programming Language :: Python :: 3.12
Requires-Dist: aiohttp-client-cache (>=0.11.0,<0.12.0)
Requires-Dist: aiosqlite (>=0.20.0,<0.21.0)
Requires-Dist: beautifulsoup4 (>=4.12,<5.0)
Requires-Dist: inscriptis (>=2.5.3,<3.0.0)
Requires-Dist: lxml (>=5.2.1,<6.0.0)
Requires-Dist: openbb-core (>=1.4.8,<2.0.0)
Requires-Dist: trafilatura (>=2.0,<3.0)
Requires-Dist: xmltodict (>=0.13.0,<0.14.0)
